pytest_aoc.py
pytest_aoc-1.23.4.dist-info/LICENSE
pytest_aoc-1.23.4.dist-info/METADATA
pytest_aoc-1.23.4.dist-info/WHEEL
pytest_aoc-1.23.4.dist-info/entry_points.txt
pytest_aoc-1.23.4.dist-info/top_level.txt
pytest_aoc-1.23.4.dist-info/RECORD
