Metadata-Version: 2.1
Name: pytest-aoc
Version: 1.23.4
Summary: Downloads puzzle inputs for Advent of Code and synthesizes PyTest fixtures
Author-email: Joost Molenaar <jjm@j0057.nl>
License: MIT
Project-URL: Homepage, https://gitlab.com/j0057-git/puzzle/pytest-aoc
Project-URL: Source, https://gitlab.com/j0057-git/puzzle/pytest-aoc
Project-URL: Tracker, https://gitlab.com/j0057-git/puzzle/pytest-aoc/-/issues
Classifier: Development Status :: 5 - Production/Stable
Classifier: Framework :: Pytest
Classifier: License :: OSI Approved :: MIT License
Classifier: Programming Language :: Python :: 3
Classifier: Programming Language :: Python :: 3 :: Only
Classifier: Programming Language :: Python :: 3.8
Classifier: Programming Language :: Python :: 3.9
Classifier: Programming Language :: Python :: 3.10
Classifier: Programming Language :: Python :: 3.11
Classifier: Programming Language :: Python :: 3.12
Classifier: Programming Language :: Python :: Implementation :: CPython
Requires-Python: >=3.8
License-File: LICENSE
Requires-Dist: requests
Requires-Dist: beautifulsoup4[html5lib]
Provides-Extra: dev
Requires-Dist: pip ; extra == 'dev'
Requires-Dist: setuptools ; extra == 'dev'
Requires-Dist: setuptools-scm ; extra == 'dev'
Requires-Dist: build ; extra == 'dev'
Requires-Dist: wheel ; extra == 'dev'
Requires-Dist: twine ; extra == 'dev'
Requires-Dist: tox ; extra == 'dev'
Provides-Extra: test
Requires-Dist: pytest ; extra == 'test'
Requires-Dist: pytest-cov ; extra == 'test'
Requires-Dist: pytest-responses ; extra == 'test'
Requires-Dist: pytest-mock ; extra == 'test'
Requires-Dist: time-machine ; extra == 'test'
